pytest_bugzilla_notifier/__init__.py
pytest_bugzilla_notifier/bugzilla_rest_client.py
pytest_bugzilla_notifier/conftest.py
pytest_bugzilla_notifier/plugin.py
pytest_bugzilla_notifier-1.1.9.dist-info/METADATA
pytest_bugzilla_notifier-1.1.9.dist-info/RECORD
pytest_bugzilla_notifier-1.1.9.dist-info/WHEEL
pytest_bugzilla_notifier-1.1.9.dist-info/entry_points.txt
pytest_bugzilla_notifier-1.1.9.dist-info/top_level.txt
