Metadata-Version: 2.1
Name: pytest-bugzilla-notifier
Version: 1.1.9
Summary: A plugin that allows you to execute create, update, and read information from BugZilla bugs
Home-page: https://github.com/mozilla-services/pytest-bugzilla-notifier
Author: Chris Hartjes
Author-email: chartjes@mozilla.com
Maintainer: Chris Hartjes
Maintainer-email: chartjes@mozilla.com
License: Mozilla Public License 2.0
Platform: UNKNOWN
Classifier: Development Status :: 4 - Beta
Classifier: Framework :: Pytest
Classifier: Intended Audience :: Developers
Classifier: Topic :: Software Development :: Testing
Classifier: Programming Language :: Python
Classifier: Programming Language :: Python :: 2
Classifier: Programming Language :: Python :: 2.7
Classifier: Programming Language :: Python :: 3
Classifier: Programming Language :: Python :: 3.3
Classifier: Programming Language :: Python :: 3.4
Classifier: Programming Language :: Python :: 3.5
Classifier: Programming Language :: Python :: Implementation :: CPython
Classifier: Operating System :: OS Independent
Requires-Dist: pytest (>=2.9.2)
Requires-Dist: requests
Requires-Dist: ConfigObj
